Metadata-Version: 2.1
Name: tes-reader
Version: 0.0.5
Summary: A module to read and parse TES (The Elder Scrolls) files.
Home-page: https://github.com/sinan-ozel/tes-reader
Author: Sinan Ozel
License: Creative Commons Zero v1.0 Universal
Platform: UNKNOWN
